{
  "ComponentAllowCustomization": true,
  "ComponentChangedSinceFileImport": true,
  "ComponentManifest": {
    "AllowAccessToGlobals": false,
    "AllowCustomization": true,
    "Description": "",
    "Name": "MiComponente",
    "TemplateGuid": "08a0452da31f4bd5bf9e9d0999829a23"
  },
  "ComponentType": "CanvasComponent",
  "CustomGroupControlTemplateName": "",
  "CustomProperties": [],
  "FirstParty": true,
  "Id": "http://microsoft.com/appmagic/Component",
  "IsComponentLocked": false,
  "IsComponentTemplate": true,
  "IsCustomGroupControlTemplate": false,
  "IsPcfControl": false,
  "IsPremiumPcfControl": false,
  "IsWidgetTemplate": false,
  "LastModifiedTimestamp": "638399825603590607",
  "Name": "08a0452da31f4bd5bf9e9d0999829a23",
  "OverridableProperties": {},
  "Version": "1.0"
}